pyeeg_toolbox/__init__.py
pyeeg_toolbox/dsp/__init__.py
pyeeg_toolbox/dsp/cwt.py
pyeeg_toolbox/dsp/detect_emi.py
pyeeg_toolbox/dsp/noise_index.py
pyeeg_toolbox/eeg_io/__init__.py
pyeeg_toolbox/eeg_io/eeg_io.py
pyeeg_toolbox/persyst/SleepStages_Reference.png
pyeeg_toolbox/persyst/an_avg_spike_amplitude.py
pyeeg_toolbox/persyst/an_plot_avg_spike_amplitude.py
pyeeg_toolbox/persyst/spike_cumulator.py
pyeeg_toolbox-0.7.0.dist-info/LICENSE
pyeeg_toolbox-0.7.0.dist-info/METADATA
pyeeg_toolbox-0.7.0.dist-info/WHEEL
pyeeg_toolbox-0.7.0.dist-info/RECORD
