Metadata-Version: 2.1
Name: pyeeg-toolbox
Version: 0.7.0
Summary: Toolbox to read, write, create montages, apply dsp transforms and conduct analysis of EEG signals
Author: dlp
Author-email: mossdet.detector@gmail.com
Requires-Python: >=3.12,<4.0
Classifier: Programming Language :: Python :: 3
Classifier: Programming Language :: Python :: 3.12
Requires-Dist: dash (>=2.18.1,<3.0.0)
Requires-Dist: edfio (>=0.4.4,<0.5.0)
Requires-Dist: edflib-python (>=1.0.8,<2.0.0)
Requires-Dist: kaleido (==0.1.0)
Requires-Dist: mne (>=1.8.0,<2.0.0)
Requires-Dist: numpy (>=2.1.1,<3.0.0)
Requires-Dist: plotly (>=5.24.1,<6.0.0)
Requires-Dist: scikit-learn (>=1.5.2,<2.0.0)
Requires-Dist: seaborn (>=0.13.2,<0.14.0)
